adaptivepatch/__init__.py
adaptivepatch/patchutils.py
adaptivepatch-0.0.1.dist-info/WHEEL
adaptivepatch-0.0.1.dist-info/METADATA
adaptivepatch-0.0.1.dist-info/RECORD
